{"nodes": [{"id": "inventory_bootstrap", "label": "Inventory Bootstrap Route", "file_type": "code", "source_file": "src/app/api/inventory/bootstrap/route.ts", "source_location": null, "source_url": null, "captured_at": null, "author": null, "contributor": null}], "edges": [{"source": "inventory_bootstrap", "target": "materials_route", "relation": "conceptually_related_to", "confidence": "INFERRED", "confidence_score": 0.85, "source_file": "src/app/api/inventory/bootstrap/route.ts", "source_location": null, "weight": 1.0}, {"source": "inventory_bootstrap", "target": "purchases_route", "relation": "conceptually_related_to", "confidence": "INFERRED", "confidence_score": 0.85, "source_file": "src/app/api/inventory/bootstrap/route.ts", "source_location": null, "weight": 1.0}], "hyperedges": [{"id": "inventory_api_flow", "label": "Inventory Management API Flow", "nodes": ["inventory_bootstrap", "materials_route", "purchases_route", "waste_route"], "relation": "participate_in", "confidence": "INFERRED", "confidence_score": 0.85, "source_file": "src/app/api/inventory/bootstrap/route.ts"}]}